setup.py
pyramid_sendmail/__init__.py
pyramid_sendmail/p_mailer.py
pyramid_sendmail/p_message.py
pyramid_sendmail/r_delivery.py
pyramid_sendmail/r_mailer.py
pyramid_sendmail.egg-info/PKG-INFO
pyramid_sendmail.egg-info/SOURCES.txt
pyramid_sendmail.egg-info/dependency_links.txt
pyramid_sendmail.egg-info/not-zip-safe
pyramid_sendmail.egg-info/requires.txt
pyramid_sendmail.egg-info/top_level.txt
tests/__init__.py