Metadata-Version: 1.0
Name: pyramid-sendmail
Version: 0.0.1
Summary: letting you use sendmail with pyramid
Home-page: https://github.com/jvanasco/pyramid_sendmail
Author: Jonathan Vanasco
Author-email: jonathan@findmeon.com
License: MIT
Keywords: web pyramid
Platform: UNKNOWN
Classifier: Intended Audience :: Developers
Classifier: Framework :: Pyramid
Classifier: Programming Language :: Python
Classifier: License :: OSI Approved :: BSD License
